LICENSE
MANIFEST.in
README.md
setup.py
pyCryptomusAPI/__init__.py
pyCryptomusAPI/api.py
pyCryptomusAPI/cryto_types.py
pyCryptomusAPI/tests.py
pyCryptomusAPI/version.py
pyCryptomusAPI.egg-info/PKG-INFO
pyCryptomusAPI.egg-info/SOURCES.txt
pyCryptomusAPI.egg-info/dependency_links.txt
pyCryptomusAPI.egg-info/top_level.txt