Metadata-Version: 2.1
Name: pyCryptomusAPI
Version: 0.1.0
Summary: Python implementation of Cryptomus (https://cryptomus.com) pubilc API
Home-page: https://github.com/Badiboy/pyCryptomusAPI
Author: Badiboy
License: MIT license
Keywords: Crypto Pay API Cryptomus
Classifier: Development Status :: 3 - Alpha
Classifier: Programming Language :: Python :: 3
Classifier: License :: OSI Approved :: MIT License
Requires: requests
License-File: LICENSE
